spool/__init__.py
spool/exceptions.py
spool/gpg.py
spool/mailer.py
spool/main.py
spool/message.py
spool/parser.py
spool/smime.py
spool-1.0.0.dist-info/LICENSE.rst
spool-1.0.0.dist-info/METADATA
spool-1.0.0.dist-info/WHEEL
spool-1.0.0.dist-info/entry_points.txt
spool-1.0.0.dist-info/top_level.txt
spool-1.0.0.dist-info/RECORD
