Metadata-Version: 2.1
Name: spool
Version: 1.0.0
Summary: Send mails with yaml
Author: Daniel Besmer
Author-email: besmerd@gmail.com
License: BSD-3-Clause
Project-URL: Documentation, https://besmerd.github.io/spool
Project-URL: Code, https://github.com/besmerd/spool
Keywords: email,mailer
Classifier: Programming Language :: Python
Classifier: Programming Language :: Python :: 3
Classifier: Programming Language :: Python :: 3.8
Classifier: Programming Language :: Python :: 3.9
Classifier: Programming Language :: Python :: 3.10
Classifier: Programming Language :: Python :: 3.11
Classifier: Programming Language :: Python :: 3.12
Requires-Python: >=3.6
License-File: LICENSE.rst
Requires-Dist: cerberus
Requires-Dist: cryptography
Requires-Dist: dkimpy
Requires-Dist: dnspython
Requires-Dist: jinja2
Requires-Dist: pyyaml
Provides-Extra: dev
Requires-Dist: mkdocs; extra == "dev"
Requires-Dist: mkdocs-material; extra == "dev"
Requires-Dist: mkdocstrings; extra == "dev"
Provides-Extra: install
Requires-Dist: setuptools-scm; extra == "install"
Provides-Extra: test
Requires-Dist: pytest; extra == "test"
